csnum/__init__.py
csnum/eigen_system.py
csnum/linear_direct_methods.py
csnum/linear_iter_methods.py
csnum/nonlinear_eqn.py
csnum/nonlinear_system.py
csnum-1.0.0.dist-info/LICENSE
csnum-1.0.0.dist-info/METADATA
csnum-1.0.0.dist-info/WHEEL
csnum-1.0.0.dist-info/top_level.txt
csnum-1.0.0.dist-info/RECORD
