Metadata-Version: 2.1
Name: csnum
Version: 1.0.0
Summary: csnum - a highly Composable and type Safe NUMerical analysis package 
Author: Yifeng He
Author-email: yfhe@ucdavis.edu
Project-URL: Bug Tracker, https://github.com/EYH0602/csnum/issues
Project-URL: Documentation, https://github.com/EYH0602/csnum/blob/main/README.md
Project-URL: Source Code, https://github.com/EYH0602/csnum
Requires-Python: >=3.10
License-File: LICENSE
